{
  "display": {
    "title": {
      "translate": "advancements.soulcoll.succory_obtained.name"
    },
    "description": {
      "translate": "advancements.soulcoll.succory_obtained.desc"
    },
    "icon": {
      "item": "soulcoll:succory"
    },
    "frame": "challenge",
    "show_toast": true,
    "announce_to_chat": true,
    "hidden": true
  },
  "rewards": {
    "experience": 100
  },
  "criteria": {
    "name": {
      "trigger": "minecraft:inventory_changed",
      "conditions": {
        "items": [
          {
            "items": [
              "soulcoll:succory"
            ]
          }
        ]
      }
    }
  },
  "parent": "soulcoll:bsingularity"
}